{
  "file_name": "girls_names_ra.json",
  "letter": "ر",
  "gender": "female",
  "names": [
    {
      "name_urdu": "راحیلہ",
      "name_hindi": "राहिला",
      "name_english": "Rahila",
      "meaning": "سفر کرنے والی، ہجرت کرنے والی",
      "detail": "یہ نام صبر اور اللہ کے راستے میں کوشش کی علامت ہے۔",
      "gender": "female"
    },
    {
      "name_urdu": "رابعہ",
      "name_hindi": "राबिया",
      "name_english": "Rabia",
      "meaning": "چوتھی، بلند مرتبہ",
      "detail": "حضرت رابعہ بصریؒ کی نسبت سے مشہور نیک نام۔",
      "gender": "female"
    },
    {
      "name_urdu": "رحمہ",
      "name_hindi": "रहमा",
      "name_english": "Rahma",
      "meaning": "رحمت، شفقت",
      "detail": "اللہ کی رحمت اور نرمی کو ظاہر کرنے والا نام۔",
      "gender": "female"
    },
    {
      "name_urdu": "رحیقہ",
      "name_hindi": "रहीका",
      "name_english": "Rahiqa",
      "meaning": "خالص مشروب، جنت کی شراب",
      "detail": "قرآن میں جنت کے پاک مشروب کا ذکر آیا ہے۔",
      "gender": "female"
    },
    {
      "name_urdu": "راضیہ",
      "name_hindi": "राज़िया",
      "name_english": "Raziya",
      "meaning": "اللہ سے راضی",
      "detail": "قناعت اور شکر کی علامت نام۔",
      "gender": "female"
    },
    {
      "name_urdu": "رابعہ",
      "name_hindi": "राबिया",
      "name_english": "Rabiah",
      "meaning": "اونچا مقام پانے والی",
      "detail": "روحانی بلندی اور تقویٰ کی علامت۔",
      "gender": "female"
    },
    {
      "name_urdu": "رمیصہ",
      "name_hindi": "रमीसा",
      "name_english": "Rameesa",
      "meaning": "چمکتی آنکھوں والی",
      "detail": "حضرت ام سلیمؓ کا لقب تھا۔",
      "gender": "female"
    },
    {
      "name_urdu": "رابعہ",
      "name_hindi": "राबिया",
      "name_english": "Rabeea",
      "meaning": "بہار، نکھار",
      "detail": "خوشحالی اور تازگی کی علامت۔",
      "gender": "female"
    },
    {
      "name_urdu": "رحاب",
      "name_hindi": "रिहाब",
      "name_english": "Rehab",
      "meaning": "کشادگی، وسعت",
      "detail": "دل کی وسعت اور اچھے اخلاق کی نشانی۔",
      "gender": "female"
    },
    {
      "name_urdu": "رانیہ",
      "name_hindi": "रानिया",
      "name_english": "Rania",
      "meaning": "نظر ڈالنے والی، غور کرنے والی",
      "detail": "سمجھ داری اور دانائی کی علامت۔",
      "gender": "female"
    },
    {
      "name_urdu": "رابع",
      "name_hindi": "राबे",
      "name_english": "Rabeh",
      "meaning": "کامیاب، نفع پانے والی",
      "detail": "دنیا و آخرت میں کامیابی کی دعا والا نام۔",
      "gender": "female"
    },
    {
      "name_urdu": "رکایا",
      "name_hindi": "रुकैया",
      "name_english": "Ruqayya",
      "meaning": "اونچا مقام، ترقی",
      "detail": "حضرت رقیہؓ بنت رسول ﷺ کے نام پر۔",
      "gender": "female"
    },
    {
      "name_urdu": "رابعہ نور",
      "name_hindi": "राबिया नूर",
      "name_english": "Rabia Noor",
      "meaning": "چوتھی روشنی",
      "detail": "نور اور ہدایت کا خوبصورت امتزاج۔",
      "gender": "female"
    },
    {
      "name_urdu": "رحیل",
      "name_hindi": "रहील",
      "name_english": "Raheel",
      "meaning": "سفر کرنے والی",
      "detail": "صبر اور جدوجہد کی علامت۔",
      "gender": "female"
    },
    {
      "name_urdu": "رانی",
      "name_hindi": "रानी",
      "name_english": "Rani",
      "meaning": "ملکہ",
      "detail": "عزت و وقار کو ظاہر کرنے والا نام۔",
      "gender": "female"
    },
    {
      "name_urdu": "رحمت",
      "name_hindi": "रहमत",
      "name_english": "Rehmat",
      "meaning": "اللہ کی رحمت",
      "detail": "برکت اور شفقت کی علامت۔",
      "gender": "female"
    },
    {
      "name_urdu": "رابعہ فاطمہ",
      "name_hindi": "राबिया फातिमा",
      "name_english": "Rabia Fatima",
      "meaning": "بلند مرتبہ فاطمہ",
      "detail": "تقویٰ اور پاکیزگی کی علامت۔",
      "gender": "female"
    },
    {
      "name_urdu": "رحیما",
      "name_hindi": "रहीमा",
      "name_english": "Raheema",
      "meaning": "نہایت رحم کرنے والی",
      "detail": "اللہ کی صفت سے ماخوذ نام۔",
      "gender": "female"
    },
    {
      "name_urdu": "رانیہ نور",
      "name_hindi": "रानिया नूर",
      "name_english": "Rania Noor",
      "meaning": "روشنی پر غور کرنے والی",
      "detail": "علم اور ہدایت کا خوبصورت مفہوم۔",
      "gender": "female"
    },
    {
      "name_urdu": "رحاب نور",
      "name_hindi": "रिहाब नूर",
      "name_english": "Rehab Noor",
      "meaning": "روشنی کی وسعت",
      "detail": "کشادہ دل اور نورانی کردار کی علامت۔",
      "gender": "female"
    }
  ]
}